{"timing":[10.0408],"date":["2026-01-20 10:06:36"],"size":[216720],"args":[],"lapse":["never"],"src":["r/france-melodi.r"],"src_hash":["3131159374acc08d5a2f50aa9069d50035bf51c4"],"arg_hash":["4262323b"],"track_hash":[0],"track":[],"wd":["file"],"qmd_file":["index.rmarkdown.qmd","annexes.rmarkdown.qmd"],"src_in":["project"],"log_file":[".sourcoise/logs/4302fd0e_2026-01-20.log"],"data_hash":["e206aa255cd773c6190b6ca201f2014a"],"uid":["4302fd0e"],"priority":[10],"cc":[95],"json_file":["/Users/xt/github/travail/.sourcoise/r/france-melodi-4262323b_4302fd0e-95.json"],"file_size":[92404],"data_date":["2025-11-22 19:04:36.014935"],"data_file":["france-melodi-4262323b_e206aa255cd773c6190b6ca201f2014a.qs2"]}
