{"timing":[7.5893],"date":["2025-11-06 11:18:25"],"size":[454088],"args":[],"lapse":["never"],"src":["france-melodi.r"],"src_hash":["08fc394d606873d50a1422e987a7e0f2ace922a5"],"arg_hash":["4262323b"],"track_hash":[0],"track":[],"wd":["file"],"qmd_file":["psal_comp.rmarkdown.qmd","index.rmarkdown.qmd"],"src_in":["project"],"log_file":{},"data_hash":["f9afccd592eb0a9d8835b71e0bcb8185"],"uid":["6773fbfa"],"priority":[10],"cc":[7],"json_file":["C:/Users/timbe/github/travail/.sourcoise/france-melodi-4262323b_6773fbfa-7.json"],"file_size":[175125],"data_date":["2025-11-06 11:18:25.116838"],"data_file":["france-melodi-4262323b_f9afccd592eb0a9d8835b71e0bcb8185.qs2"]}
