{"timing":[2.3694],"date":["2025-09-24 15:53:51"],"size":[118968],"args":[],"lapse":["never"],"src":["snf_ratio.r"],"src_hash":["5576e85b75e73e457e172011fae8ea9c6fd50ce3"],"arg_hash":["4262323b"],"track_hash":[0],"track":[],"wd":["file"],"qmd_file":["psal_comp.rmarkdown.qmd"],"src_in":["project"],"log_file":{},"data_hash":["5b01813ad80cba5c98cd809f0bfd0c44"],"uid":["6773fbfa"],"priority":[10],"cc":[11],"json_file":["C:/Users/timbe/github/travail/.sourcoise/snf_ratio-4262323b_6773fbfa-11.json"],"file_size":[29485],"data_date":["2025-09-24 15:53:51.564579"],"data_file":["snf_ratio-4262323b_5b01813ad80cba5c98cd809f0bfd0c44.qs2"]}
